snutshell/__init__.py
snutshell-1.3.dist-info/LICENSE.txt
snutshell-1.3.dist-info/METADATA
snutshell-1.3.dist-info/WHEEL
snutshell-1.3.dist-info/top_level.txt
snutshell-1.3.dist-info/RECORD
