Metadata-Version: 2.1
Name: snutshell
Version: 1.3
Summary: create xlsx and dat file from python list, tuple, dictionary, numpy array
Home-page: UNKNOWN
Author: arn
Author-email: naziul.arnab@gmail.com
License: MIT
Keywords: simulation
Platform: UNKNOWN
Classifier: Development Status :: 5 - Production/Stable
Classifier: Intended Audience :: Education
Classifier: Operating System :: Microsoft :: Windows :: Windows 10
Classifier: License :: OSI Approved :: MIT License
Classifier: Programming Language :: Python :: 3
Requires-Dist: numpy
Requires-Dist: XlsxWriter
